setup.py
brynq_sdk_google_drive/__init__.py
brynq_sdk_google_drive/google_drive.py
brynq_sdk_google_drive.egg-info/PKG-INFO
brynq_sdk_google_drive.egg-info/SOURCES.txt
brynq_sdk_google_drive.egg-info/dependency_links.txt
brynq_sdk_google_drive.egg-info/not-zip-safe
brynq_sdk_google_drive.egg-info/requires.txt
brynq_sdk_google_drive.egg-info/top_level.txt