Metadata-Version: 1.0
Name: brynq-sdk-google-drive
Version: 1.0.1
Summary: Google Drive wrapper from BrynQ
Home-page: UNKNOWN
Author: BrynQ
Author-email: support@brynq.com
License: BrynQ License
Platform: UNKNOWN
